{
  "compiled_snapshot_hash": "sha256:602ba1e3ce8a857252842a7dc5226d0171778838872b2dde867dc350589c98fb",
  "control_plane": {
    "audit": "jcs_json",
    "authoring": "yaml",
    "capabilities_snapshot_hash": "sha256:d2b8bf2cdae622bbf711bb32e89c35a5863bb206ac048dbdfc681e693aaafd33",
    "compiled_snapshot_hash": "sha256:602ba1e3ce8a857252842a7dc5226d0171778838872b2dde867dc350589c98fb",
    "compiled_snapshot_location": ".vac/cache/compiled",
    "compiled_snapshots_current": true,
    "generated_mirror_location": ".vac/registry/compiled",
    "runtime": "compiled_json"
  },
  "control_plane_version": "1.9",
  "confirmed_intent": {
    "confirmed_intent_domain_coverage": "SV-Pass",
    "confirmed_intent_traceability_gate": "SV-Pass",
    "confirmed_intent_traceability": "SV-Pass",
    "confirmed_intent_negative_fixtures": "SV-Pass",
    "confirmed_intent_executable_fixtures": "SV-Pass",
    "all_negative_cases_rejected": true,
    "crate_without_intent_or_rationale": 0,
    "external_provider_remote_process_io_e2e": "TV-Pending",
    "domain_count": 7,
    "domain_map": "tests/fixtures/confirmed-intent/domain-map.json",
    "coverage_audit": "docs/audit/VAC_CONFIRMED_INTENT_COVERAGE_AUDIT.md",
    "traceability_audit": "docs/audit/VAC_CONFIRMED_INTENT_TRACEABILITY.md",
    "domains": [
      "vac-broker",
      "vac-provider-core",
      "vac-mcp-server",
      "vac-messaging-gateway",
      "vac-remote-service",
      "vac-autopilot",
      "vac-tui-bridge"
    ]
  },
  "enforcement_level": "L1",
  "generated_at": "1970-01-01T00:00:00Z",
  "id": "status.workspace.current",
  "kind": "registry_status",
  "model": null,
  "product": "VAC",
  "profile": "default",
  "provider": null,
  "readiness": {
    "deprecated": 0,
    "effective_percent": 0,
    "partial": 24,
    "planned": 1,
    "ready": 0,
    "source": "canonical compiled capabilities/current.json; cargo gates not evaluated",
    "valid_percent": 0
  },
  "readiness_summary": {
    "deprecated": 0,
    "partial": 24,
    "planned": 1,
    "ready": 0,
    "total": 25
  },
  "rulebook": "vac.core",
  "runtime": {
    "compiled_cache": ".vac/cache/compiled",
    "gateway_default": false,
    "jobs": ".vac/registry/runtime/jobs.json",
    "journal": ".vac/db/runtime.db",
    "server_default": false
  },
  "runtime_authority": "compiled_json",
  "runtime_jobs": {
    "queued": 0,
    "running": 0
  },
  "runtime_mode": "local-control-plane",
  "rust_workspace": "vac-rs",
  "schema_version": 1,
  "spec_sync": {
    "unresolved_critical_drift": 0
  },
  "storage_class": {
    "authority_manifests": "tracked",
    "compiled_snapshot": "cache_or_db",
    "generated_artifacts": "export_only_by_default",
    "runtime_journal": "local_sqlite_ignored"
  },
  "tv_pending": [
    "cargo_metadata",
    "cargo_fmt",
    "cargo_check",
    "cargo_clippy",
    "cargo_test"
  ],
  "updated_at": "1970-01-01T00:00:00Z",
  "workspace": {
    "conformance_level": "L1",
    "enforcement_level": "L1",
    "file_count": 756,
    "rust_crate_count": 38
  },
  "rust_ast_index": {
    "rust_ast_index": "SV-Pass",
    "parser_mode": "rust_ast",
    "ast_symbols_detected": true,
    "rust_ast_default_index": "SV-Pass",
    "fail_closed_fallback": true,
    "heuristic_ast_delta_reported": true,
    "ast_index_does_not_overclaim_calls": true,
    "calls_lightweight": "SV-Partial",
    "complete_call_graph": "Not claimed",
    "default_index_parser": "rust_ast_default",
    "fallback_mode": "fail_closed_static_heuristic",
    "ast_lane": "default_syn",
    "fixture_dir": "tests/fixtures/index/rust-ast",
    "delta_audit": "docs/audit/VAC_RUST_AST_INDEX_DELTA.md"
  }
}
